brain/__init__.py
thebrain-1.0.dist-info/LICENSE
thebrain-1.0.dist-info/METADATA
thebrain-1.0.dist-info/WHEEL
thebrain-1.0.dist-info/top_level.txt
thebrain-1.0.dist-info/RECORD
